{
  "topic": "Histograms",
  "board": "CIE 0580",
  "subtopicId": "cie0580:statistics-e9:e9-07-histograms",
  "syllabusCode": "E9-07",
  "tier": "Extended",
  "domain": "statistics",
  "questions": [
    {
      "type": "multiple-choice",
      "questionText": "Which formula correctly links frequency, class width, and frequency density?",
      "options": [
        "frequency density = frequency / class width",
        "frequency density = frequency × class width",
        "frequency density = class width / frequency",
        "frequency density = frequency + class width"
      ],
      "correctAnswer": 0,
      "explanation": "Frequency density is defined as the frequency per unit of class width. Therefore, the correct formula is frequency density = frequency / class width."
    },
    {
      "type": "multiple-choice",
      "questionText": "In a histogram, a class interval has a width of 10 and a frequency of 40. What is the frequency density?",
      "options": [
        "4",
        "400",
        "0.25",
        "50"
      ],
      "correctAnswer": 0,
      "explanation": "Frequency density = frequency / class width = 40 / 10 = 4."
    },
    {
      "type": "multiple-choice",
      "questionText": "The bar for a class in a histogram has a frequency density of 6 and the class width is 5. What is the frequency for this class?",
      "options": [
        "1.2",
        "11",
        "30",
        "1"
      ],
      "correctAnswer": 2,
      "explanation": "Frequency = frequency density × class width = 6 × 5 = 30."
    },
    {
      "type": "multiple-choice",
      "questionText": "In a histogram with bars of unequal width, what does the area of each bar represent?",
      "options": [
        "Frequency density",
        "Class width",
        "Frequency",
        "Cumulative frequency"
      ],
      "correctAnswer": 2,
      "explanation": "The area of a bar is calculated as height × width, which is frequency density × class width. This product is equal to the frequency."
    },
    {
      "type": "multiple-choice",
      "questionText": "A class in a histogram has a frequency of 75 and a frequency density of 15. What is the class width?",
      "options": [
        "5",
        "1125",
        "0.2",
        "90"
      ],
      "correctAnswer": 0,
      "explanation": "Class width = frequency / frequency density = 75 / 15 = 5."
    },
    {
      "type": "multiple-choice",
      "questionText": "True or False: In a histogram with unequal class widths, the tallest bar always represents the class with the highest frequency.",
      "options": [
        "True, height is proportional to frequency.",
        "False, a wider, shorter bar could have a larger area.",
        "True, because the y-axis is frequency.",
        "False, the widest bar always has the highest frequency."
      ],
      "correctAnswer": 1,
      "explanation": "The height of a bar represents frequency density, not frequency. Frequency is the area of the bar. A short, wide bar can have a greater area (frequency) than a tall, narrow bar."
    },
    {
      "type": "multiple-choice",
      "questionText": "A histogram is drawn to show the heights of plants. The bar for the interval 10 cm < h ≤ 25 cm has a height (frequency density) of 3. How many plants are in this interval?",
      "options": [
        "15",
        "5",
        "45",
        "3"
      ],
      "correctAnswer": 2,
      "explanation": "The class width is 25 - 10 = 15 cm. The frequency is frequency density × class width = 3 × 15 = 45."
    },
    {
      "type": "multiple-choice",
      "questionText": "Histograms are primarily used for what type of data?",
      "options": [
        "Ungrouped discrete data",
        "Grouped continuous data",
        "Qualitative data",
        "Paired data"
      ],
      "correctAnswer": 1,
      "explanation": "Histograms are designed to show the distribution of grouped continuous data, where the bars touch to indicate the continuous nature of the variable."
    },
    {
      "type": "multiple-choice",
      "questionText": "A histogram bar for the class `30 ≤ x < 40` has a frequency of 50. A bar for `40 ≤ x < 60` has a frequency of 80. Which bar is taller?",
      "options": [
        "The bar for 30 ≤ x < 40",
        "The bar for 40 ≤ x < 60",
        "They have the same height",
        "Cannot be determined"
      ],
      "correctAnswer": 0,
      "explanation": "The height represents frequency density. For 30 ≤ x < 40, width=10, density=50/10=5. For 40 ≤ x < 60, width=20, density=80/20=4. The first bar is taller."
    },
    {
      "type": "multiple-choice",
      "questionText": "The weights, w kg, of 120 parcels are measured. In the histogram, the bar representing 5 < w ≤ 10 has a frequency density of 8. What is the frequency for this class?",
      "options": [
        "1.6",
        "40",
        "8",
        "16"
      ],
      "correctAnswer": 1,
      "explanation": "The class width is 10 - 5 = 5. The frequency = frequency density × class width = 8 × 5 = 40."
    },
    {
      "type": "multiple-choice",
      "questionText": "If two bars in a histogram have the exact same area, what must be true about them?",
      "options": [
        "They have the same height.",
        "They have the same class width.",
        "They have the same frequency.",
        "They have the same frequency density and width."
      ],
      "correctAnswer": 2,
      "explanation": "Since the area of a bar in a histogram represents its frequency, equal areas mean equal frequencies, regardless of their individual heights or widths."
    },
    {
      "type": "multiple-choice",
      "questionText": "A histogram has two bars. Bar 1: class `0-10`, density `5`. Bar 2: class `10-30`, density `2`. What is the total frequency represented?",
      "options": [
        "7",
        "90",
        "30",
        "100"
      ],
      "correctAnswer": 1,
      "explanation": "Frequency of Bar 1 = 5 × (10-0) = 50. Frequency of Bar 2 = 2 × (30-10) = 40. Total frequency = 50 + 40 = 90."
    }
  ]
}
